{
	"conditions" : {
	},
	"paired" : {
		"zad_DeviousBoots" : [
			{
				"A1" : {
					"animation" : [ "Leito_Feet_A1_S1", "Leito_Feet_A1_S2" ], 
					"reqConstraints" : 0, 
					"optConstraints" : 258
				}, 
				"A2" : {
					"animation" : [ "Leito_Feet_A2_S1", "Leito_Feet_A2_S2" ], 
					"reqConstraints" : 0, 
					"optConstraints" : 10
				}, 
				"isSequence" : true, 
				"lewd" : 0, 
				"aggressive" : 0
			}, {
				"A1" : {
					"animation" : [ "Leito_Feet_A1_S1", "Leito_Feet_A1_S2", "Leito_Feet_A1_S3", "Leito_Feet_A1_S4" ], 
					"reqConstraints" : 0, 
					"optConstraints" : 256
				}, 
				"A2" : {
					"animation" : [ "Leito_Feet_A2_S1", "Leito_Feet_A2_S2", "Leito_Feet_A2_S3", "Leito_Feet_A2_S4" ], 
					"reqConstraints" : 0, 
					"optConstraints" : 0
				}, 
				"isSequence" : true, 
				"lewd" : 0, 
				"aggressive" : 0
			}, {
				"A1" : {
					"animation" : [ "Leito_Feet_A1_S1" ], 
					"reqConstraints" : 0, 
					"optConstraints" : 259
				}, 
				"A2" : {
					"animation" : [ "Leito_Feet_A2_S1" ], 
					"reqConstraints" : 0, 
					"optConstraints" : 10
				}, 
				"isSequence" : true, 
				"lewd" : 0, 
				"aggressive" : 0
			}, {
				"A1" : {
					"animation" : [ "Leito_Feet2_A1_S1", "Leito_Feet2_A1_S2", "Leito_Feet2_A1_S3" ], 
					"reqConstraints" : 0, 
					"optConstraints" : 259
				}, 
				"A2" : {
					"animation" : [ "Leito_Feet2_A2_S1", "Leito_Feet2_A2_S2", "Leito_Feet2_A2_S3" ], 
					"reqConstraints" : 0, 
					"optConstraints" : 10
				}, 
				"isSequence" : true, 
				"lewd" : 0, 
				"aggressive" : 0
			}, {
				"A1" : {
					"animation" : [ "Leito_Feet3_A1_S1", "Leito_Feet3_A1_S2", "Leito_Feet3_A1_S3", "Leito_Feet3_A1_S4" ], 
					"reqConstraints" : 0, 
					"optConstraints" : 259
				}, 
				"A2" : {
					"animation" : [ "Leito_Feet3_A2_S1", "Leito_Feet3_A2_S2", "Leito_Feet3_A2_S3", "Leito_Feet3_A2_S4" ], 
					"reqConstraints" : 0, 
					"optConstraints" : 10
				}, 
				"isSequence" : true, 
				"lewd" : 0, 
				"aggressive" : 0
			}
		], 
		"zad_DeviousPlug" : [
			
		], 
		"zad_DeviousBelt" : [
			
		], 
		"zad_DeviousBra" : [
			
		], 
		"zad_DeviousCollar" : [
			
		], 
		"zad_DeviousArmCuffs" : [
			
		], 
		"zad_DeviousLegCuffs" : [
			{
				"A1" : {
					"animation" : [ "Leito_Feet_A1_S1", "Leito_Feet_A1_S2" ], 
					"reqConstraints" : 0, 
					"optConstraints" : 258
				}, 
				"A2" : {
					"animation" : [ "Leito_Feet_A2_S1", "Leito_Feet_A2_S2" ], 
					"reqConstraints" : 0, 
					"optConstraints" : 10
				}, 
				"isSequence" : true, 
				"lewd" : 0, 
				"aggressive" : 0
			}, {
				"A1" : {
					"animation" : [ "Leito_Feet_A1_S1", "Leito_Feet_A1_S2", "Leito_Feet_A1_S3", "Leito_Feet_A1_S4" ], 
					"reqConstraints" : 0, 
					"optConstraints" : 256
				}, 
				"A2" : {
					"animation" : [ "Leito_Feet_A2_S1", "Leito_Feet_A2_S2", "Leito_Feet_A2_S3", "Leito_Feet_A2_S4" ], 
					"reqConstraints" : 0, 
					"optConstraints" : 0
				}, 
				"isSequence" : true, 
				"lewd" : 0, 
				"aggressive" : 0
			}, {
				"A1" : {
					"animation" : [ "Leito_Feet_A1_S1" ], 
					"reqConstraints" : 0, 
					"optConstraints" : 259
				}, 
				"A2" : {
					"animation" : [ "Leito_Feet_A2_S1" ], 
					"reqConstraints" : 0, 
					"optConstraints" : 10
				}, 
				"isSequence" : true, 
				"lewd" : 0, 
				"aggressive" : 0
			}, {
				"A1" : {
					"animation" : [ "Leito_Feet2_A1_S1", "Leito_Feet2_A1_S2", "Leito_Feet2_A1_S3" ], 
					"reqConstraints" : 0, 
					"optConstraints" : 259
				}, 
				"A2" : {
					"animation" : [ "Leito_Feet2_A2_S1", "Leito_Feet2_A2_S2", "Leito_Feet2_A2_S3" ], 
					"reqConstraints" : 0, 
					"optConstraints" : 10
				}, 
				"isSequence" : true, 
				"lewd" : 0, 
				"aggressive" : 0
			}, {
				"A1" : {
					"animation" : [ "Leito_Feet3_A1_S1", "Leito_Feet3_A1_S2", "Leito_Feet3_A1_S3", "Leito_Feet3_A1_S4" ], 
					"reqConstraints" : 0, 
					"optConstraints" : 259
				}, 
				"A2" : {
					"animation" : [ "Leito_Feet3_A2_S1", "Leito_Feet3_A2_S2", "Leito_Feet3_A2_S3", "Leito_Feet3_A2_S4" ], 
					"reqConstraints" : 0, 
					"optConstraints" : 10
				}, 
				"isSequence" : true, 
				"lewd" : 0, 
				"aggressive" : 0
			}
		], 
		"zad_DeviousArmbinder" : [
			
		], 
		"zad_DeviousArmbinderElbow" : [
			
		], 
		"zad_DeviousHobbleSkirt" : [
			{
				"A1" : {
					"animation" : [ "Leito_Feet_A1_S1" ], 
					"reqConstraints" : 0, 
					"optConstraints" : 259
				}, 
				"A2" : {
					"animation" : [ "Leito_Feet_A2_S1" ], 
					"reqConstraints" : 0, 
					"optConstraints" : 10
				}, 
				"isSequence" : true, 
				"lewd" : 0, 
				"aggressive" : 0
			}, {
				"A1" : {
					"animation" : [ "Leito_Feet2_A1_S1", "Leito_Feet2_A1_S2", "Leito_Feet2_A1_S3" ], 
					"reqConstraints" : 0, 
					"optConstraints" : 259
				}, 
				"A2" : {
					"animation" : [ "Leito_Feet2_A2_S1", "Leito_Feet2_A2_S2", "Leito_Feet2_A2_S3" ], 
					"reqConstraints" : 0, 
					"optConstraints" : 10
				}, 
				"isSequence" : true, 
				"lewd" : 0, 
				"aggressive" : 0
			}
		], 
		"zad_DeviousHobbleSkirtRelaxed" : [
			
		], 
		"zad_DeviousAnkleShackles" : [
			{
				"A1" : {
					"animation" : [ "Leito_Feet_A1_S1", "Leito_Feet_A1_S2" ], 
					"reqConstraints" : 0, 
					"optConstraints" : 258
				}, 
				"A2" : {
					"animation" : [ "Leito_Feet_A2_S1", "Leito_Feet_A2_S2" ], 
					"reqConstraints" : 0, 
					"optConstraints" : 10
				}, 
				"isSequence" : true, 
				"lewd" : 0, 
				"aggressive" : 0
			}, {
				"A1" : {
					"animation" : [ "Leito_Feet_A1_S1" ], 
					"reqConstraints" : 0, 
					"optConstraints" : 259
				}, 
				"A2" : {
					"animation" : [ "Leito_Feet_A2_S1" ], 
					"reqConstraints" : 0, 
					"optConstraints" : 10
				}, 
				"isSequence" : true, 
				"lewd" : 0, 
				"aggressive" : 0
			}, {
				"A1" : {
					"animation" : [ "Leito_Feet2_A1_S1", "Leito_Feet2_A1_S2", "Leito_Feet2_A1_S3" ], 
					"reqConstraints" : 0, 
					"optConstraints" : 259
				}, 
				"A2" : {
					"animation" : [ "Leito_Feet2_A2_S1", "Leito_Feet2_A2_S2", "Leito_Feet2_A2_S3" ], 
					"reqConstraints" : 0, 
					"optConstraints" : 10
				}, 
				"isSequence" : true, 
				"lewd" : 0, 
				"aggressive" : 0
			}, {
				"A1" : {
					"animation" : [ "Leito_Feet3_A1_S1", "Leito_Feet3_A1_S2", "Leito_Feet3_A1_S3", "Leito_Feet3_A1_S4" ], 
					"reqConstraints" : 0, 
					"optConstraints" : 259
				}, 
				"A2" : {
					"animation" : [ "Leito_Feet3_A2_S1", "Leito_Feet3_A2_S2", "Leito_Feet3_A2_S3", "Leito_Feet3_A2_S4" ], 
					"reqConstraints" : 0, 
					"optConstraints" : 10
				}, 
				"isSequence" : true, 
				"lewd" : 0, 
				"aggressive" : 0
			}
		], 
		"zad_DeviousStraitJacket" : [
			
		], 
		"zad_DeviousCuffsFront" : [
			
		], 
		"zad_DeviousPetSuit" : [
			
		], 
		"zad_DeviousYoke" : [
			
		], 
		"zad_DeviousYokeBB" : [
			
		], 
		"zad_DeviousCorset" : [
			
		], 
		"zad_DeviousClamps" : [
			
		], 
		"zad_DeviousGloves" : [
			
		], 
		"zad_DeviousHood" : [
			
		], 
		"zad_DeviousElbowTie" : [
			
		], 
		"zad_DeviousGag" : [
			
		], 
		"zad_DeviousGagLarge" : [
			
		], 
		"zad_DeviousGagPanel" : [
			
		], 
		"zad_DeviousPlugVaginal" : [
			
		], 
		"zad_DeviousPlugAnal" : [
			
		], 
		"zad_DeviousHarness" : [
			
		], 
		"zad_DeviousBlindfold" : [
			
		], 
		"zad_DeviousPiercingsNipple" : [
			
		], 
		"zad_DeviousPiercingsVaginal" : [
			
		], 
		"zad_DeviousBondageMittens" : [
			
		], 
		"zad_DeviousSuit" : [
			{
				"A1" : {
					"animation" : [ "Leito_Feet_A1_S1", "Leito_Feet_A1_S2" ], 
					"reqConstraints" : 0, 
					"optConstraints" : 258
				}, 
				"A2" : {
					"animation" : [ "Leito_Feet_A2_S1", "Leito_Feet_A2_S2" ], 
					"reqConstraints" : 0, 
					"optConstraints" : 10
				}, 
				"isSequence" : true, 
				"lewd" : 0, 
				"aggressive" : 0
			}, {
				"A1" : {
					"animation" : [ "Leito_Feet_A1_S1", "Leito_Feet_A1_S2", "Leito_Feet_A1_S3", "Leito_Feet_A1_S4" ], 
					"reqConstraints" : 0, 
					"optConstraints" : 256
				}, 
				"A2" : {
					"animation" : [ "Leito_Feet_A2_S1", "Leito_Feet_A2_S2", "Leito_Feet_A2_S3", "Leito_Feet_A2_S4" ], 
					"reqConstraints" : 0, 
					"optConstraints" : 0
				}, 
				"isSequence" : true, 
				"lewd" : 0, 
				"aggressive" : 0
			}, {
				"A1" : {
					"animation" : [ "Leito_Feet_A1_S1" ], 
					"reqConstraints" : 0, 
					"optConstraints" : 259
				}, 
				"A2" : {
					"animation" : [ "Leito_Feet_A2_S1" ], 
					"reqConstraints" : 0, 
					"optConstraints" : 10
				}, 
				"isSequence" : true, 
				"lewd" : 0, 
				"aggressive" : 0
			}, {
				"A1" : {
					"animation" : [ "Leito_Feet2_A1_S1", "Leito_Feet2_A1_S2", "Leito_Feet2_A1_S3" ], 
					"reqConstraints" : 0, 
					"optConstraints" : 259
				}, 
				"A2" : {
					"animation" : [ "Leito_Feet2_A2_S1", "Leito_Feet2_A2_S2", "Leito_Feet2_A2_S3" ], 
					"reqConstraints" : 0, 
					"optConstraints" : 10
				}, 
				"isSequence" : true, 
				"lewd" : 0, 
				"aggressive" : 0
			}, {
				"A1" : {
					"animation" : [ "Leito_Feet3_A1_S1", "Leito_Feet3_A1_S2", "Leito_Feet3_A1_S3", "Leito_Feet3_A1_S4" ], 
					"reqConstraints" : 0, 
					"optConstraints" : 259
				}, 
				"A2" : {
					"animation" : [ "Leito_Feet3_A2_S1", "Leito_Feet3_A2_S2", "Leito_Feet3_A2_S3", "Leito_Feet3_A2_S4" ], 
					"reqConstraints" : 0, 
					"optConstraints" : 10
				}, 
				"isSequence" : true, 
				"lewd" : 0, 
				"aggressive" : 0
			}
		]
	}
}